{
  "id": "AHKS-20230407-01",
  "type": "综合分析·政治素养·党性修养",
  "province": "安徽",
  "fullScore": 25.0,
  "question": "习总书记强调：“我们共产党人为的是大公、守的是大义、求的是大我。”请你谈谈对“大”的理解。",
  "dimensions": [
    {
      "name": "①核心内涵理解",
      "score": 7.0
    },
    {
      "name": "②精神意义论述",
      "score": 8.0
    },
    {
      "name": "③乡镇岗位结合",
      "score": 6.0
    },
    {
      "name": "④自身践行表态",
      "score": 3.0
    },
    {
      "name": "⑤语言逻辑",
      "score": 1.0
    }
  ],
  "coreKeywords": [
    "大公",
    "大义",
    "大我",
    "公心",
    "信仰",
    "忠诚",
    "为民",
    "担当"
  ],
  "strongKeywords": [
    "安徽",
    "乡镇岗",
    "基层",
    "乡村振兴",
    "实干",
    "奉献",
    "初心"
  ],
  "weakKeywords": [],
  "bonusKeywords": [
    "一心为公",
    "忠诚担当",
    "甘于奉献",
    "扎根基层",
    "服务群众"
  ],
  "penaltyKeywords": [
    "理解偏差",
    "内容空洞",
    "脱离岗位",
    "脱离实际",
    "逻辑混乱"
  ],
  "scoringCriteria": [
    "①核心内涵理解（7分）：准确把握大公、大义、大我的深刻内涵",
    "②精神意义论述（8分）：对政治品格、价值追求、使命担当论述全面充分",
    "③乡镇岗位结合（6分）：贴合基层、扎根一线、服务群众、担当作为",
    "④自身践行表态（3分）：态度真诚、方向明确、务实有力",
    "⑤语言逻辑（1分）：表述规范、条理清晰、层次分明。"
  ],
  "deductionRules": [
    "①政治理解偏差、脱离“大公大义大我”核心主题，扣6—9分",
    "②论述空泛、内容单薄、缺乏层次、无说服力，扣5—8分",
    "③未结合乡镇基层、乡村振兴、安徽实际，扣4—6分",
    "④表态空洞、缺乏担当、脱离岗位，扣2—4分",
    "⑤逻辑混乱、口语化严重、表述不连贯，扣2—3分"
  ],
  "sourceDocument": "2020-2025第二批次完全版.docx",
  "referenceAnswer": "总书记的论述深刻阐明了共产党人的精神境界与价值追求，“大公、大义、大我”三个“大”字，道出了我们党的初心使命、政治品格与责任担当，是新时代基层干部的立身之本、成事之基、履职之要。 第一，为的是“大公”，就是坚守公心、一心为民。大公就是心中装着人民、凡事想着群众、工作为了群众，不谋私利、不徇私情，把群众利益放在最高位置，这是我们党赢得民心的根本所在。 第二，守的是“大义”，就是坚守信仰、忠诚担当。大义就是对党忠诚、对人民忠诚、对事业忠诚，在大是大非面前立场坚定，在风险挑战面前挺身而出，在基层一线勇挑重担，坚守正道、弘扬正气。 第三，求的是“大我”，就是甘于奉献、成就人民。大我就是把个人追求融入国家发展、安徽建设、基层事业，舍小家为大家、以小我成大我，在乡村振兴、基层治理、服务群众中实现人生价值。 第四，立足乡镇岗位践行“三大”要求。作为安徽乡镇基层干部，我将始终牢记总书记嘱托，坚守大公之心、恪守大义之行、追求大我之境，扎根江淮大地、服务基层群众、实干担当作为，用心用情用力办好群众每一件实事，做一名让组织放心、让群众满意的基层干部。",
  "tags": [
    "安徽",
    "省考",
    "乡镇岗",
    "面试",
    "综合分析",
    "大公",
    "大义",
    "大我",
    "政治素养",
    "基层干部",
    "为民服务",
    "实干担当"
  ],
  "scoreBands": [
    {
      "label": "低分/偏弱",
      "min_score": 0,
      "max_score": 13.8,
      "description": "核心要点覆盖不足，结构或岗位适配明显欠缺。"
    },
    {
      "label": "基本合格",
      "min_score": 13.9,
      "max_score": 17.5,
      "description": "能覆盖主要要求，但深度、结构或本土化仍有短板。"
    },
    {
      "label": "中高档",
      "min_score": 17.6,
      "max_score": 21.2,
      "description": "内容较完整，逻辑较清晰，接近高分答案。"
    },
    {
      "label": "高分标杆",
      "min_score": 21.3,
      "max_score": 25.0,
      "description": "高分参考答案区间，用于回归验证。"
    }
  ],
  "regressionCases": [
    {
      "label": "文档高分基准答案",
      "sample_path": "assets/regression_samples/generated_anhui/AHKS-20230407-01/reference_high.txt",
      "expected_min": 22.0,
      "expected_max": 25.0,
      "llmExpectedMin": 22.0,
      "llmExpectedMax": 25.0,
      "notes": "来自原始题库文档的核心采分基准答案。"
    },
    {
      "label": "程序化中档参考答案",
      "sample_path": "assets/regression_samples/generated_anhui/AHKS-20230407-01/reference_mid.txt",
      "expected_min": 9.8,
      "expected_max": 13.6,
      "llmExpectedMin": 11.1,
      "llmExpectedMax": 15.2,
      "notes": "基于高分答案程序化压缩生成；策略=template_analysis_mid_1，句数=6，截断=none，关键词削弱=medium。"
    },
    {
      "label": "程序化低档参考答案",
      "sample_path": "assets/regression_samples/generated_anhui/AHKS-20230407-01/reference_low.txt",
      "expected_min": 6.8,
      "expected_max": 10.6,
      "llmExpectedMin": 5.9,
      "llmExpectedMax": 10.6,
      "notes": "基于高分答案程序化降档生成；策略=template_analysis_low_1，句数=5，截断=none，关键词削弱=medium，口语化=是。"
    }
  ]
}